FishScrapping/__init__.py
FishScrapping/fishbase.py
FishScrapping/fishbase_bold.py
FishScrapping/worms.py
FishScrapping-1.2.data/scripts/fishbase.py
FishScrapping-1.2.dist-info/LICENSE
FishScrapping-1.2.dist-info/METADATA
FishScrapping-1.2.dist-info/WHEEL
FishScrapping-1.2.dist-info/top_level.txt
FishScrapping-1.2.dist-info/RECORD
