Metadata-Version: 2.1
Name: FishScrapping
Version: 1.2
Summary: UNKNOWN
Home-page: https://github.com/Ulises-Rosas/FishScrapping
Author: Ulises Rosas
Author-email: ulisesfrosasp@gmail.com
License: UNKNOWN
Platform: UNKNOWN
Classifier: Programming Language :: Python :: 3
Classifier: License :: OSI Approved :: MIT License
